gramps.py
gramps_gui-0.0.data/scripts/gramps.py
gramps_gui-0.0.dist-info/METADATA
gramps_gui-0.0.dist-info/WHEEL
gramps_gui-0.0.dist-info/top_level.txt
gramps_gui-0.0.dist-info/RECORD
