Metadata-Version: 2.1
Name: gramps-gui
Version: 0.0
Summary: Addons for the Gramps genealogy program
Home-page: https://github.com/gramps-project/addons
Author: The Gramps Project
Author-email: nick-h@gramps-project.org
Classifier: Development Status :: 1 - Planning
Classifier: Topic :: Sociology :: Genealogy
